pygame_shaders/__init__.py
pygame_shaders/pygame_shaders.py
pygame_shaders/screen_rect.py
pygame_shaders/shader_utils.py
pygame_shaders/texture.py
pygame_shaders-2.0.2.dist-info/licenses/LICENSE
pygame_shaders-2.0.2.dist-info/METADATA
pygame_shaders-2.0.2.dist-info/WHEEL
pygame_shaders-2.0.2.dist-info/top_level.txt
pygame_shaders-2.0.2.dist-info/RECORD
