Metadata-Version: 2.4
Name: pygame_shaders
Version: 2.0.2
Summary: a library to easily integrate shaders into your new or existing pygame projects
Home-page: https://github.com/ScriptLineStudios/pygame_shaders
Author: ScriptLine Studios
Author-email: scriptlinestudios@protonmail.com
Classifier: Programming Language :: Python :: 3
Classifier: License :: OSI Approved :: MIT License
Classifier: Operating System :: OS Independent
License-File: LICENSE
Requires-Dist: numpy
Requires-Dist: moderngl
Dynamic: license-file
